napari_segselect/__init__.py
napari_segselect/_reader.py
napari_segselect/_widget.py
napari_segselect/_writer.py
napari_segselect/napari.yaml
napari_segselect/_tests/__init__.py
napari_segselect/_tests/test_reader.py
napari_segselect/_tests/test_widget.py
napari_segselect-0.1.3.dist-info/LICENSE
napari_segselect-0.1.3.dist-info/METADATA
napari_segselect-0.1.3.dist-info/WHEEL
napari_segselect-0.1.3.dist-info/entry_points.txt
napari_segselect-0.1.3.dist-info/top_level.txt
napari_segselect-0.1.3.dist-info/RECORD
