Metadata-Version: 2.2
Name: napari-segselect
Version: 0.1.3
Summary: Select a connected component from a membrain-seg segmentation.
Author: Benedikt Wimmer
Author-email: b.wimmer@bioc.uzh.ch
License: 
Project-URL: Bug Tracker, https://github.com/bwmr/napari-segselect/issues
Project-URL: Documentation, https://github.com/bwmr/napari-segselect#README.md
Project-URL: Source Code, https://github.com/bwmr/napari-segselect
Project-URL: User Support, https://github.com/bwmr/napari-segselect/issues
Classifier: Development Status :: 2 - Pre-Alpha
Classifier: Framework :: napari
Classifier: Intended Audience :: Developers
Classifier: License :: OSI Approved :: BSD License
Classifier: Operating System :: OS Independent
Classifier: Programming Language :: Python
Classifier: Programming Language :: Python :: 3
Classifier: Programming Language :: Python :: 3 :: Only
Classifier: Programming Language :: Python :: 3.9
Classifier: Programming Language :: Python :: 3.10
Classifier: Programming Language :: Python :: 3.11
Classifier: Programming Language :: Python :: 3.12
Classifier: Topic :: Scientific/Engineering :: Image Processing
Requires-Python: >=3.9
License-File: LICENSE
Requires-Dist: numpy
Requires-Dist: magicgui
Requires-Dist: mrcfile
Requires-Dist: scipy
Provides-Extra: testing
Requires-Dist: napari; extra == "testing"
Requires-Dist: ruff; extra == "testing"
